countSyn.v
module counter (
    clk, rst, count, m_in
);
    integer m;
    input clk, rst;
    output reg [31:0] count;
    output reg [31:0] m_in;
    
    always @(posedge clk or posedge rst) begin
        if (rst) 
            begin
                count = 32'b0;
                m <= 0;
                m_in <= 0;
            end
        else 
            begin
                m <= +m;
                m_in <= m;
                count = count + 1;
            end
    end
endmodule

countSyn_tb.v
module countSyn_tb;
    reg clk, rst;
    wire [31:0] count;
    wire [31:0] m_in;
    counter LUT (.clk(clk), .rst(rst), .count(count), .m_in(m_in));

    initial begin
        clk = 0;
        forever begin
            #5 clk = ~clk;
        end
    end

    initial begin
        clk = 0;
        rst = 0;
        $dumpfile ("countSyn.vcd");
        $dumpvars(0, countSyn_tb);
        $monitor("clk = %b, rst = %b, count = %d, m_in = %d", clk, rst, count, m_in);

        rst = 1;
        #10;
        rst = 0;

        #100;

        $finish;   
    end
endmodule

countSyn.vcd
$date
	Mon Jan 20 15:50:00 2025
$end
$version
	Icarus Verilog
$end
$timescale
	1s
$end
$scope module countSyn_tb $end
$var wire 32 ! m_in [31:0] $end
$var wire 32 " count [31:0] $end
$var reg 1 # clk $end
$var reg 1 $ rst $end
$scope module LUT $end
$var wire 1 # clk $end
$var wire 1 $ rst $end
$var reg 32 % count [31:0] $end
$var reg 32 & m_in [31:0] $end
$var integer 32 ' m [31:0] $end
$upscope $end
$upscope $end
$enddefinitions $end
$comment Show the parameter values. $end
$dumpall
$end
#0
$dumpvars
b0 '
b0 &
b0 %
1$
0#
b0 "
b0 !
$end
#5
1#
#10
0#
0$
#15
b1 "
b1 %
1#
#20
0#
#25
b10 "
b10 %
1#
#30
0#
#35
b11 "
b11 %
1#
#40
0#
#45
b100 "
b100 %
1#
#50
0#
#55
b101 "
b101 %
1#
#60
0#
#65
b110 "
b110 %
1#
#70
0#
#75
b111 "
b111 %
1#
#80
0#
#85
b1000 "
b1000 %
1#
#90
0#
#95
b1001 "
b1001 %
1#
#100
0#
#105
b1010 "
b1010 %
1#
