detector.v
module mealy (
    clk, a, b, reset
);
    input clk, a, reset;
    output reg b;
    parameter S0 = 2'b00, S1 = 2'b01, S2 = 2'b10, S3 = 2'b11;
    reg [1 : 0] PS, NS;
    always @(posedge clk or posedge reset) begin
        if (reset) begin
            PS <= S0;
        end
        else PS <= NS;
    end

    always @(PS, a) begin
        b = 0;
        case (PS)
            S0 : begin
                if (a == 0) begin
                    NS = S1;
                end
                else if (a == 1) begin
                        NS = S0;
                end
                end 
            S1 : begin
                if (a == 1) begin
                    NS = S2;
                end
                else if (a == 0) begin
                    NS = S1;
                end
            end
            S2 : begin
                if (a == 1) begin
                    NS = S3;
                end
                else if (a == 0) begin
                    NS = S1;
                end
            end
            S3 : begin
                if (a == 0) begin
                    NS = S1;
                    b = 1;
                end
                else if (a == 0) begin
                    NS = S0;
                end
            end
        endcase
    end
endmodule

detector_tb.v
module mealy_tb;
    reg a, clk, reset;
    wire b;

    mealy DUT (.a(a), .clk(clk), .reset(reset), .b(b));

    initial begin
        clk = 0; reset = 1; #10 reset = 0;
    end
    always #5 clk = ~clk;
    initial begin
        $dumpfile("detector.vcd");
        $dumpvars(0, mealy_tb);
        $monitor($time, " ", "a = %b, reset = %b, b = %b", a, reset, b);
        #10 a = 0;
        #10 a = 1;
        #10 a = 1;
        #10 a = 0; // This should trigger z = 1 (detecting "0110")

        #20 a = 1; 
        #10 a = 1; 
        #10 a = 0; // Another "0110" detection
        
        #10 $finish;
    end
endmodule

detector.vcd
$date
	Tue Feb 11 17:54:24 2025
$end
$version
	Icarus Verilog
$end
$timescale
	1s
$end
$scope module mealy_tb $end
$var wire 1 ! b $end
$var reg 1 " a $end
$var reg 1 # clk $end
$var reg 1 $ reset $end
$scope module DUT $end
$var wire 1 " a $end
$var wire 1 # clk $end
$var wire 1 $ reset $end
$var parameter 2 % S0 $end
$var parameter 2 & S1 $end
$var parameter 2 ' S2 $end
$var parameter 2 ( S3 $end
$var reg 2 ) NS [1:0] $end
$var reg 2 * PS [1:0] $end
$var reg 1 ! b $end
$upscope $end
$upscope $end
$enddefinitions $end
$comment Show the parameter values. $end
$dumpall
b11 (
b10 '
b1 &
b0 %
$end
#0
$dumpvars
b0 *
bx )
1$
0#
x"
0!
$end
#5
1#
#10
b1 )
0#
0"
0$
#15
b1 *
1#
#20
b10 )
0#
1"
#25
b11 )
b10 *
1#
#30
0#
#35
b11 *
1#
#40
1!
b1 )
0#
0"
#45
0!
b1 *
1#
#50
0#
#55
1#
#60
b10 )
0#
1"
#65
b11 )
b10 *
1#
#70
0#
#75
b11 *
1#
#80
1!
b1 )
0#
0"
#85
0!
b1 *
1#
