controller_moore.v
`ifndef CONTR0LLER_MOORE_V
`define CONTR0LLER_MOORE_V

module controller(
    clk, rst, start, clt, cgt, ceq, done, ldA, ldB, sel1, sel2, sel3, sel4
);
    input clk, rst, start;
    input clt, ceq, cgt;
    output reg done, ldA, ldB;
    output reg sel1, sel2, sel3, sel4;
    reg [2 : 0] PState, NState;
    parameter S0 = 3'b000, S1 = 3'b001, S2 = 3'b010, S3 = 3'b011,
                S4 = 3'b100, S5 = 3'b101, S6 = 3'b110;

    always @(posedge clk, posedge rst) begin
        if (rst) begin
            PState <= S0;
        end
        else PState <= NState;
    end

    always @(*) begin
        case (PState)
            S0 : begin 
                ldA = 1'b0;
                ldB = 1'b0;
                done = 1'b0;
                sel1 = 1'bx;
                sel2 = 1'bx;
                sel3 = 1'bx;
                sel4 = 1'bx;

                if (start) begin
                    NState = S1;
                end
                else NState = S0;
            end
            S1 : begin
                ldA = 1'b1;
                sel1 = 1'b1;
                ldB = 1'b0;
                sel2 = 1'b0;
                sel3 = 1'bx;
                sel4 = 1'bx;
                done = 1'b0;

                NState = S2;
            end
            S2 : begin
                ldA = 1'b0;
                ldB = 1'b1;
                sel1 = 1'bx;
                sel2 = 1'b1;
                sel3 = 1'bx;
                sel4 = 1'bx;
                done = 1'b0;

                NState = S3;
            end
            S3 : begin
                ldA = 1'b0;
                ldB = 1'b0;
                sel1 = 1'bx;
                sel2 = 1'bx;
                sel3 = 1'bx;
                sel4 = 1'bx;
                done = 1'b0;

                if (clt == 1'b1 && cgt == 1'b0 && ceq == 1'b0) begin
                    NState = S4;
                end
                else if (clt == 1'b0 && cgt == 1'b1 && ceq == 1'b0) begin
                    NState = S5;
                end
                else if (clt == 1'b0 && cgt == 1'b0 && ceq == 1'b1) begin
                    NState = S6;
                end
            end
            S4 : begin
                ldA = 1'b0;
                ldB = 1'b1;
                sel1 = 1'bx;
                sel2 = 1'b0;
                sel3 = 1'b0;
                sel4 = 1'b1;
                done = 1'b0;

                NState = S3;
            end
            S5 : begin
                ldA = 1'b1;
                ldB = 1'b0;
                sel1 = 1'b0;
                sel2 = 1'bx;
                sel3 = 1'b1;
                sel4 = 1'b0;
                done = 1'b0;

                NState = S3;
            end
            S6 : begin
                ldA = 1'b0;
                ldB = 1'b0;
                sel1 = 1'bx;
                sel2 = 1'bx;
                sel3 = 1'bx;
                sel4 = 1'bx;
                done = 1'b1;
                
                NState = S0;
            end
        endcase
    end
endmodule
`endif

datapath2.v
`ifndef DATAPATH2_V
`define DATAPATH2_V

module Load_reg (
    inp, outp, load, reset, clk
);
    input [15 : 0] inp;
    input clk, reset, load;
    output reg [15 : 0] outp;
    reg [15 : 0] temp;
    
    always @(posedge clk, posedge reset) begin
        if (reset) begin
            temp <= 16'b0;
        end
        else if (load) begin
            temp <= inp;
        end
    end

    always @(*) begin
        outp = temp;
    end
endmodule

module compare (
    a, b, lt, gt, eq
);
    input [15 : 0] a, b;
    output reg lt, gt, eq;
    
    always @(*) begin
        if (a > b) begin
            lt = 1'b0;
            eq = 1'b0;
            gt = 1'b1;
        end
        else if (a < b) begin
            lt = 1'b1;
            gt = 1'b0;
            eq = 1'b0;
        end
        else if (a == b) begin
            lt = 1'b0;
            gt = 1'b0;
            eq = 1'b1;
        end
    end
endmodule

module subtract (
    a, b, sub
);
    input [15 : 0] a, b;
    output [15 : 0] sub;

    assign sub = a - b;
endmodule

module mux21 (
    a, b, sel, out
);
    input [15 : 0] a, b;
    input sel;
    output reg [15 : 0] out;

    always @(*) begin
        if (sel == 1'b1) begin
            out = a;
        end
        else if (sel == 1'b0) begin
            out = b;
        end
    end
endmodule 

module datapath (
    clk, rst, done, inp, outp, sel1, sel2, sel3, sel4, temp_lt, temp_gt, temp_eq, load_A, load_B
);
    input clk, rst;
    input [15 : 0] inp;
    input sel1, sel2, sel3, sel4;
    input load_A, load_B;
    output reg [15 : 0] outp;
    input done;
    output temp_lt, temp_gt, temp_eq;
    wire [15 : 0] temp_M1, output_SUB, temp_M2, out_A, out_B, temp_M3, temp_M4;
    mux21 M (
        .a(inp),
        .b(output_SUB),
        .sel(sel1),
        .out(temp_M1)
    );

    mux21 M1 (
        .a(inp),
        .b(output_SUB),
        .sel(sel2),
        .out(temp_M2)
    );

    Load_reg A (
        .clk(clk),
        .reset(rst),
        .inp(temp_M1),
        .load(load_A),
        .outp(out_A)
    );

    Load_reg B (
        .clk(clk),
        .reset(rst),
        .inp(temp_M2),
        .load(load_B),
        .outp(out_B)
    );

    compare C (
        .a(out_A),
        .b(out_B),
        .lt(temp_lt), 
        .gt(temp_gt),
        .eq(temp_eq)
    );

    mux21 M2 (
        .a(out_A),
        .b(out_B),
        .sel(sel3),
        .out(temp_M3)
    );

    mux21 M3 (
        .a(out_A),
        .b(out_B),
        .sel(sel4),
        .out(temp_M4)
    );

    subtract S (
        .a(temp_M3),
        .b(temp_M4),
        .sub(output_SUB)
    );

    always @(*) begin
        outp = (done == 1'b1) ? out_A : 16'bz;
    end

endmodule

`endif

ex2_tb.v
`include "controller_moore.v"
`include "datapath2.v"

module tb;
    reg clk, rst, start;
    reg [15 : 0] data_in;
    wire [15 : 0] data_out;
    wire temp_sel1, temp_sel2, temp_sel3, temp_sel4;    
    wire lt, gt, eq;
    wire load_A, load_B;
    wire done;
    integer i;

    datapath DP (
        .clk(clk),
        .rst(rst), 
        .done(done),
        .inp(data_in), 
        .outp(data_out), 
        .sel1(temp_sel1), 
        .sel2(temp_sel2),
        .sel3(temp_sel3), 
        .sel4(temp_sel4), 
        .temp_lt(lt), 
        .temp_gt(gt), 
        .temp_eq(eq), 
        .load_A(load_A), 
        .load_B(load_B)
    );

    controller CT (
        .clk(clk),
        .rst(rst), 
        .done(done), 
        .clt(lt), 
        .cgt(gt), 
        .ceq(eq), 
        .sel1(temp_sel1), 
        .sel2(temp_sel2), 
        .sel3(temp_sel3), 
        .sel4(temp_sel4),
        .ldA(load_A), 
        .ldB(load_B), 
        .start(start)
    );

    initial begin
        clk = 1'b0;
        rst = 1'b1;
        start = 1'b0;
        i = 0;
        #5; rst = 1'b0;
    end
    always #5 clk = ~clk;
    initial begin
        $dumpfile("ex2.vcd");
        $dumpvars(0, tb);
    end
    initial begin
        #10;
        @(posedge clk);
        repeat(10) begin
            @(negedge clk);
            start = 1'b1;
            @(negedge clk);
            data_in = $urandom_range(1, 256);
            $display($time, " ", "Number 1 = %d", data_in);
            @(negedge clk);
            data_in = $urandom_range(1, 256);
            $display($time, " ", "Number 2 = %d", data_in);
            @(posedge done);
            @(negedge clk);
            @(negedge clk);
            start = 1'b0;
            i = i + 1;
        end
        #10; $finish;
    end
    initial begin
        forever @(posedge done) begin
            #0;
            $display($time, " ", "Result = %d", data_out);
        end
    end
endmodule

ex2.vcd
$date
	Sat Mar 01 08:56:40 2025
$end
$version
	Icarus Verilog
$end
$timescale
	1s
$end
$scope module tb $end
$var wire 1 ! temp_sel4 $end
$var wire 1 " temp_sel3 $end
$var wire 1 # temp_sel2 $end
$var wire 1 $ temp_sel1 $end
$var wire 1 % lt $end
$var wire 1 & load_B $end
$var wire 1 ' load_A $end
$var wire 1 ( gt $end
$var wire 1 ) eq $end
$var wire 1 * done $end
$var wire 16 + data_out [15:0] $end
$var reg 1 , clk $end
$var reg 16 - data_in [15:0] $end
$var reg 1 . rst $end
$var reg 1 / start $end
$var integer 32 0 i [31:0] $end
$scope module CT $end
$var wire 1 , clk $end
$var wire 1 . rst $end
$var wire 1 / start $end
$var wire 1 % clt $end
$var wire 1 ( cgt $end
$var wire 1 ) ceq $end
$var parameter 3 1 S0 $end
$var parameter 3 2 S1 $end
$var parameter 3 3 S2 $end
$var parameter 3 4 S3 $end
$var parameter 3 5 S4 $end
$var parameter 3 6 S5 $end
$var parameter 3 7 S6 $end
$var reg 3 8 NState [2:0] $end
$var reg 3 9 PState [2:0] $end
$var reg 1 * done $end
$var reg 1 ' ldA $end
$var reg 1 & ldB $end
$var reg 1 $ sel1 $end
$var reg 1 # sel2 $end
$var reg 1 " sel3 $end
$var reg 1 ! sel4 $end
$upscope $end
$scope module DP $end
$var wire 1 , clk $end
$var wire 1 * done $end
$var wire 16 : inp [15:0] $end
$var wire 1 ' load_A $end
$var wire 1 & load_B $end
$var wire 1 . rst $end
$var wire 1 $ sel1 $end
$var wire 1 # sel2 $end
$var wire 1 " sel3 $end
$var wire 1 ! sel4 $end
$var wire 1 % temp_lt $end
$var wire 1 ( temp_gt $end
$var wire 1 ) temp_eq $end
$var wire 16 ; temp_M4 [15:0] $end
$var wire 16 < temp_M3 [15:0] $end
$var wire 16 = temp_M2 [15:0] $end
$var wire 16 > temp_M1 [15:0] $end
$var wire 16 ? output_SUB [15:0] $end
$var wire 16 @ out_B [15:0] $end
$var wire 16 A out_A [15:0] $end
$var reg 16 B outp [15:0] $end
$scope module A $end
$var wire 1 , clk $end
$var wire 1 ' load $end
$var wire 1 . reset $end
$var wire 16 C inp [15:0] $end
$var reg 16 D outp [15:0] $end
$var reg 16 E temp [15:0] $end
$upscope $end
$scope module B $end
$var wire 1 , clk $end
$var wire 1 & load $end
$var wire 1 . reset $end
$var wire 16 F inp [15:0] $end
$var reg 16 G outp [15:0] $end
$var reg 16 H temp [15:0] $end
$upscope $end
$scope module C $end
$var wire 16 I a [15:0] $end
$var wire 16 J b [15:0] $end
$var reg 1 ) eq $end
$var reg 1 ( gt $end
$var reg 1 % lt $end
$upscope $end
$scope module M $end
$var wire 16 K a [15:0] $end
$var wire 1 $ sel $end
$var wire 16 L b [15:0] $end
$var reg 16 M out [15:0] $end
$upscope $end
$scope module M1 $end
$var wire 16 N a [15:0] $end
$var wire 1 # sel $end
$var wire 16 O b [15:0] $end
$var reg 16 P out [15:0] $end
$upscope $end
$scope module M2 $end
$var wire 16 Q a [15:0] $end
$var wire 16 R b [15:0] $end
$var wire 1 " sel $end
$var reg 16 S out [15:0] $end
$upscope $end
$scope module M3 $end
$var wire 16 T a [15:0] $end
$var wire 16 U b [15:0] $end
$var wire 1 ! sel $end
$var reg 16 V out [15:0] $end
$upscope $end
$scope module S $end
$var wire 16 W a [15:0] $end
$var wire 16 X b [15:0] $end
$var wire 16 Y sub [15:0] $end
$upscope $end
$upscope $end
$upscope $end
$enddefinitions $end
$comment Show the parameter values. $end
$dumpall
b110 7
b101 6
b100 5
b11 4
b10 3
b1 2
b0 1
$end
#0
$dumpvars
bx Y
bx X
bx W
bx V
b0 U
b0 T
bx S
b0 R
b0 Q
bx P
bx O
bx N
bx M
bx L
bx K
b0 J
b0 I
b0 H
b0 G
bx F
b0 E
b0 D
bx C
bz B
b0 A
b0 @
bx ?
bx >
bx =
bx <
bx ;
bx :
b0 9
b0 8
b0 0
0/
1.
bx -
0,
bz +
0*
1)
0(
0'
0&
0%
x$
x#
x"
x!
$end
#5
1,
0.
#10
0,
#15
1,
#20
b1 8
1/
0,
#25
b10 8
0#
1$
1'
b1 9
1,
#30
b10010011 >
b10010011 C
b10010011 M
b10010011 -
b10010011 :
b10010011 K
b10010011 N
0,
#35
1(
0)
b10010011 =
b10010011 F
b10010011 P
b10010011 A
b10010011 D
b10010011 I
b10010011 Q
b10010011 T
b11 8
1#
x$
1&
0'
b10010011 E
b10 9
1,
#40
b1000001 =
b1000001 F
b1000001 P
b1000001 -
b1000001 :
b1000001 K
b1000001 N
0,
#45
b101 8
x#
0&
b1000001 @
b1000001 G
b1000001 J
b1000001 R
b1000001 U
b11 9
b1000001 H
1,
#50
0,
#55
b1010010 ?
b1010010 L
b1010010 O
b1010010 Y
b1000001 ;
b1000001 V
b1000001 X
b10010011 <
b10010011 S
b10010011 W
b1010010 >
b1010010 C
b1010010 M
b11 8
0!
1"
0$
1'
b101 9
1,
#60
0,
#65
b101 8
x!
x"
x$
0'
b1010010 A
b1010010 D
b1010010 I
b1010010 Q
b1010010 T
b11 9
b1010010 E
1,
#70
0,
#75
b10001 >
b10001 C
b10001 M
b10001 ?
b10001 L
b10001 O
b10001 Y
b1010010 <
b1010010 S
b1010010 W
b11 8
0!
1"
0$
1'
b101 9
1,
#80
0,
#85
0(
1%
b100 8
x!
x"
x$
0'
b10001 A
b10001 D
b10001 I
b10001 Q
b10001 T
b11 9
b10001 E
1,
#90
0,
#95
b10001 ;
b10001 V
b10001 X
b110000 ?
b110000 L
b110000 O
b110000 Y
b1000001 <
b1000001 S
b1000001 W
b110000 =
b110000 F
b110000 P
b11 8
1!
0"
0#
1&
b100 9
1,
#100
0,
#105
b100 8
x!
x"
x#
0&
b110000 @
b110000 G
b110000 J
b110000 R
b110000 U
b11 9
b110000 H
1,
#110
0,
#115
b11111 =
b11111 F
b11111 P
b11111 ?
b11111 L
b11111 O
b11111 Y
b110000 <
b110000 S
b110000 W
b11 8
1!
0"
0#
1&
b100 9
1,
#120
0,
#125
b100 8
x!
x"
x#
0&
b11111 @
b11111 G
b11111 J
b11111 R
b11111 U
b11 9
b11111 H
1,
#130
0,
#135
b1110 =
b1110 F
b1110 P
b1110 ?
b1110 L
b1110 O
b1110 Y
b11111 <
b11111 S
b11111 W
b11 8
1!
0"
0#
1&
b100 9
1,
#140
0,
#145
1(
0%
b101 8
x!
x"
x#
0&
b1110 @
b1110 G
b1110 J
b1110 R
b1110 U
b11 9
b1110 H
1,
#150
0,
#155
b1110 ;
b1110 V
b1110 X
b11 ?
b11 L
b11 O
b11 Y
b10001 <
b10001 S
b10001 W
b11 >
b11 C
b11 M
b11 8
0!
1"
0$
1'
b101 9
1,
#160
0,
#165
0(
1%
b100 8
x!
x"
x$
0'
b11 A
b11 D
b11 I
b11 Q
b11 T
b11 9
b11 E
1,
#170
0,
#175
b11 ;
b11 V
b11 X
b1011 ?
b1011 L
b1011 O
b1011 Y
b1110 <
b1110 S
b1110 W
b1011 =
b1011 F
b1011 P
b11 8
1!
0"
0#
1&
b100 9
1,
#180
0,
#185
b100 8
x!
x"
x#
0&
b1011 @
b1011 G
b1011 J
b1011 R
b1011 U
b11 9
b1011 H
1,
#190
0,
#195
b1000 =
b1000 F
b1000 P
b1000 ?
b1000 L
b1000 O
b1000 Y
b1011 <
b1011 S
b1011 W
b11 8
1!
0"
0#
1&
b100 9
1,
#200
0,
#205
b100 8
x!
x"
x#
0&
b1000 @
b1000 G
b1000 J
b1000 R
b1000 U
b11 9
b1000 H
1,
#210
0,
#215
b101 =
b101 F
b101 P
b101 ?
b101 L
b101 O
b101 Y
b1000 <
b1000 S
b1000 W
b11 8
1!
0"
0#
1&
b100 9
1,
#220
0,
#225
b100 8
x!
x"
x#
0&
b101 @
b101 G
b101 J
b101 R
b101 U
b11 9
b101 H
1,
#230
0,
#235
b10 =
b10 F
b10 P
b10 ?
b10 L
b10 O
b10 Y
b101 <
b101 S
b101 W
b11 8
1!
0"
0#
1&
b100 9
1,
#240
0,
#245
1(
0%
b101 8
x!
x"
x#
0&
b10 @
b10 G
b10 J
b10 R
b10 U
b11 9
b10 H
1,
#250
0,
#255
b10 ;
b10 V
b10 X
b1 ?
b1 L
b1 O
b1 Y
b11 <
b11 S
b11 W
b1 >
b1 C
b1 M
b11 8
0!
1"
0$
1'
b101 9
1,
#260
0,
#265
0(
1%
b100 8
x!
x"
x$
0'
b1 A
b1 D
b1 I
b1 Q
b1 T
b11 9
b1 E
1,
#270
0,
#275
b1 ;
b1 V
b1 X
b1 ?
b1 L
b1 O
b1 Y
b10 <
b10 S
b10 W
b1 =
b1 F
b1 P
b11 8
1!
0"
0#
1&
b100 9
1,
#280
0,
#285
1)
0%
b110 8
x!
x"
x#
0&
b1 @
b1 G
b1 J
b1 R
b1 U
b11 9
b1 H
1,
#290
0,
#295
b1 +
b1 B
b0 8
1*
b110 9
1,
#300
0,
#305
bz +
bz B
b1 8
0*
b0 9
1,
#310
b0 8
b1 0
0/
0,
#315
1,
#320
b1 8
1/
0,
#325
b1000001 >
b1000001 C
b1000001 M
b10 8
0#
1$
1'
b1 9
1,
#330
b101 >
b101 C
b101 M
b101 -
b101 :
b101 K
b101 N
0,
#335
1(
0)
b101 =
b101 F
b101 P
b101 A
b101 D
b101 I
b101 Q
b101 T
b11 8
1#
x$
1&
0'
b101 E
b10 9
1,
#340
b110010 =
b110010 F
b110010 P
b110010 -
b110010 :
b110010 K
b110010 N
0,
#345
0(
1%
b100 8
x#
0&
b110010 @
b110010 G
b110010 J
b110010 R
b110010 U
b11 9
b110010 H
1,
#350
0,
#355
b101 ;
b101 V
b101 X
b101101 ?
b101101 L
b101101 O
b101101 Y
b110010 <
b110010 S
b110010 W
b101101 =
b101101 F
b101101 P
b11 8
1!
0"
0#
1&
b100 9
1,
#360
0,
#365
b100 8
x!
x"
x#
0&
b101101 @
b101101 G
b101101 J
b101101 R
b101101 U
b11 9
b101101 H
1,
#370
0,
#375
b101000 =
b101000 F
b101000 P
b101000 ?
b101000 L
b101000 O
b101000 Y
b101101 <
b101101 S
b101101 W
b11 8
1!
0"
0#
1&
b100 9
1,
#380
0,
#385
b100 8
x!
x"
x#
0&
b101000 @
b101000 G
b101000 J
b101000 R
b101000 U
b11 9
b101000 H
1,
#390
0,
#395
b100011 =
b100011 F
b100011 P
b100011 ?
b100011 L
b100011 O
b100011 Y
b101000 <
b101000 S
b101000 W
b11 8
1!
0"
0#
1&
b100 9
1,
#400
0,
#405
b100 8
x!
x"
x#
0&
b100011 @
b100011 G
b100011 J
b100011 R
b100011 U
b11 9
b100011 H
1,
#410
0,
#415
b11110 =
b11110 F
b11110 P
b11110 ?
b11110 L
b11110 O
b11110 Y
b100011 <
b100011 S
b100011 W
b11 8
1!
0"
0#
1&
b100 9
1,
#420
0,
#425
b100 8
x!
x"
x#
0&
b11110 @
b11110 G
b11110 J
b11110 R
b11110 U
b11 9
b11110 H
1,
#430
0,
#435
b11001 =
b11001 F
b11001 P
b11001 ?
b11001 L
b11001 O
b11001 Y
b11110 <
b11110 S
b11110 W
b11 8
1!
0"
0#
1&
b100 9
1,
#440
0,
#445
b100 8
x!
x"
x#
0&
b11001 @
b11001 G
b11001 J
b11001 R
b11001 U
b11 9
b11001 H
1,
#450
0,
#455
b10100 =
b10100 F
b10100 P
b10100 ?
b10100 L
b10100 O
b10100 Y
b11001 <
b11001 S
b11001 W
b11 8
1!
0"
0#
1&
b100 9
1,
#460
0,
#465
b100 8
x!
x"
x#
0&
b10100 @
b10100 G
b10100 J
b10100 R
b10100 U
b11 9
b10100 H
1,
#470
0,
#475
b1111 =
b1111 F
b1111 P
b1111 ?
b1111 L
b1111 O
b1111 Y
b10100 <
b10100 S
b10100 W
b11 8
1!
0"
0#
1&
b100 9
1,
#480
0,
#485
b100 8
x!
x"
x#
0&
b1111 @
b1111 G
b1111 J
b1111 R
b1111 U
b11 9
b1111 H
1,
#490
0,
#495
b1010 =
b1010 F
b1010 P
b1010 ?
b1010 L
b1010 O
b1010 Y
b1111 <
b1111 S
b1111 W
b11 8
1!
0"
0#
1&
b100 9
1,
#500
0,
#505
b100 8
x!
x"
x#
0&
b1010 @
b1010 G
b1010 J
b1010 R
b1010 U
b11 9
b1010 H
1,
#510
0,
#515
b101 =
b101 F
b101 P
b101 ?
b101 L
b101 O
b101 Y
b1010 <
b1010 S
b1010 W
b11 8
1!
0"
0#
1&
b100 9
1,
#520
0,
#525
1)
0%
b110 8
x!
x"
x#
0&
b101 @
b101 G
b101 J
b101 R
b101 U
b11 9
b101 H
1,
#530
0,
#535
b101 +
b101 B
b0 8
1*
b110 9
1,
#540
0,
#545
bz +
bz B
b1 8
0*
b0 9
1,
#550
b0 8
b10 0
0/
0,
#555
1,
#560
b1 8
1/
0,
#565
b110010 >
b110010 C
b110010 M
b10 8
0#
1$
1'
b1 9
1,
#570
b10000111 >
b10000111 C
b10000111 M
b10000111 -
b10000111 :
b10000111 K
b10000111 N
0,
#575
1(
0)
b10000111 =
b10000111 F
b10000111 P
b10000111 A
b10000111 D
b10000111 I
b10000111 Q
b10000111 T
b11 8
1#
x$
1&
0'
b10000111 E
b10 9
1,
#580
b11000111 =
b11000111 F
b11000111 P
b11000111 -
b11000111 :
b11000111 K
b11000111 N
0,
#585
0(
1%
b100 8
x#
0&
b11000111 @
b11000111 G
b11000111 J
b11000111 R
b11000111 U
b11 9
b11000111 H
1,
#590
0,
#595
b10000111 ;
b10000111 V
b10000111 X
b1000000 ?
b1000000 L
b1000000 O
b1000000 Y
b11000111 <
b11000111 S
b11000111 W
b1000000 =
b1000000 F
b1000000 P
b11 8
1!
0"
0#
1&
b100 9
1,
#600
0,
#605
1(
0%
b101 8
x!
x"
x#
0&
b1000000 @
b1000000 G
b1000000 J
b1000000 R
b1000000 U
b11 9
b1000000 H
1,
#610
0,
#615
b1000000 ;
b1000000 V
b1000000 X
b1000111 ?
b1000111 L
b1000111 O
b1000111 Y
b10000111 <
b10000111 S
b10000111 W
b1000111 >
b1000111 C
b1000111 M
b11 8
0!
1"
0$
1'
b101 9
1,
#620
0,
#625
b101 8
x!
x"
x$
0'
b1000111 A
b1000111 D
b1000111 I
b1000111 Q
b1000111 T
b11 9
b1000111 E
1,
#630
0,
#635
b111 >
b111 C
b111 M
b111 ?
b111 L
b111 O
b111 Y
b1000111 <
b1000111 S
b1000111 W
b11 8
0!
1"
0$
1'
b101 9
1,
#640
0,
#645
0(
1%
b100 8
x!
x"
x$
0'
b111 A
b111 D
b111 I
b111 Q
b111 T
b11 9
b111 E
1,
#650
0,
#655
b111 ;
b111 V
b111 X
b111001 ?
b111001 L
b111001 O
b111001 Y
b1000000 <
b1000000 S
b1000000 W
b111001 =
b111001 F
b111001 P
b11 8
1!
0"
0#
1&
b100 9
1,
#660
0,
#665
b100 8
x!
x"
x#
0&
b111001 @
b111001 G
b111001 J
b111001 R
b111001 U
b11 9
b111001 H
1,
#670
0,
#675
b110010 =
b110010 F
b110010 P
b110010 ?
b110010 L
b110010 O
b110010 Y
b111001 <
b111001 S
b111001 W
b11 8
1!
0"
0#
1&
b100 9
1,
#680
0,
#685
b100 8
x!
x"
x#
0&
b110010 @
b110010 G
b110010 J
b110010 R
b110010 U
b11 9
b110010 H
1,
#690
0,
#695
b101011 =
b101011 F
b101011 P
b101011 ?
b101011 L
b101011 O
b101011 Y
b110010 <
b110010 S
b110010 W
b11 8
1!
0"
0#
1&
b100 9
1,
#700
0,
#705
b100 8
x!
x"
x#
0&
b101011 @
b101011 G
b101011 J
b101011 R
b101011 U
b11 9
b101011 H
1,
#710
0,
#715
b100100 =
b100100 F
b100100 P
b100100 ?
b100100 L
b100100 O
b100100 Y
b101011 <
b101011 S
b101011 W
b11 8
1!
0"
0#
1&
b100 9
1,
#720
0,
#725
b100 8
x!
x"
x#
0&
b100100 @
b100100 G
b100100 J
b100100 R
b100100 U
b11 9
b100100 H
1,
#730
0,
#735
b11101 =
b11101 F
b11101 P
b11101 ?
b11101 L
b11101 O
b11101 Y
b100100 <
b100100 S
b100100 W
b11 8
1!
0"
0#
1&
b100 9
1,
#740
0,
#745
b100 8
x!
x"
x#
0&
b11101 @
b11101 G
b11101 J
b11101 R
b11101 U
b11 9
b11101 H
1,
#750
0,
#755
b10110 =
b10110 F
b10110 P
b10110 ?
b10110 L
b10110 O
b10110 Y
b11101 <
b11101 S
b11101 W
b11 8
1!
0"
0#
1&
b100 9
1,
#760
0,
#765
b100 8
x!
x"
x#
0&
b10110 @
b10110 G
b10110 J
b10110 R
b10110 U
b11 9
b10110 H
1,
#770
0,
#775
b1111 =
b1111 F
b1111 P
b1111 ?
b1111 L
b1111 O
b1111 Y
b10110 <
b10110 S
b10110 W
b11 8
1!
0"
0#
1&
b100 9
1,
#780
0,
#785
b100 8
x!
x"
x#
0&
b1111 @
b1111 G
b1111 J
b1111 R
b1111 U
b11 9
b1111 H
1,
#790
0,
#795
b1000 =
b1000 F
b1000 P
b1000 ?
b1000 L
b1000 O
b1000 Y
b1111 <
b1111 S
b1111 W
b11 8
1!
0"
0#
1&
b100 9
1,
#800
0,
#805
b100 8
x!
x"
x#
0&
b1000 @
b1000 G
b1000 J
b1000 R
b1000 U
b11 9
b1000 H
1,
#810
0,
#815
b1 =
b1 F
b1 P
b1 ?
b1 L
b1 O
b1 Y
b1000 <
b1000 S
b1000 W
b11 8
1!
0"
0#
1&
b100 9
1,
#820
0,
#825
1(
0%
b101 8
x!
x"
x#
0&
b1 @
b1 G
b1 J
b1 R
b1 U
b11 9
b1 H
1,
#830
0,
#835
b1 ;
b1 V
b1 X
b110 ?
b110 L
b110 O
b110 Y
b111 <
b111 S
b111 W
b110 >
b110 C
b110 M
b11 8
0!
1"
0$
1'
b101 9
1,
#840
0,
#845
b101 8
x!
x"
x$
0'
b110 A
b110 D
b110 I
b110 Q
b110 T
b11 9
b110 E
1,
#850
0,
#855
b101 >
b101 C
b101 M
b101 ?
b101 L
b101 O
b101 Y
b110 <
b110 S
b110 W
b11 8
0!
1"
0$
1'
b101 9
1,
#860
0,
#865
b101 8
x!
x"
x$
0'
b101 A
b101 D
b101 I
b101 Q
b101 T
b11 9
b101 E
1,
#870
0,
#875
b100 >
b100 C
b100 M
b100 ?
b100 L
b100 O
b100 Y
b101 <
b101 S
b101 W
b11 8
0!
1"
0$
1'
b101 9
1,
#880
0,
#885
b101 8
x!
x"
x$
0'
b100 A
b100 D
b100 I
b100 Q
b100 T
b11 9
b100 E
1,
#890
0,
#895
b11 >
b11 C
b11 M
b11 ?
b11 L
b11 O
b11 Y
b100 <
b100 S
b100 W
b11 8
0!
1"
0$
1'
b101 9
1,
#900
0,
#905
b101 8
x!
x"
x$
0'
b11 A
b11 D
b11 I
b11 Q
b11 T
b11 9
b11 E
1,
#910
0,
#915
b10 >
b10 C
b10 M
b10 ?
b10 L
b10 O
b10 Y
b11 <
b11 S
b11 W
b11 8
0!
1"
0$
1'
b101 9
1,
#920
0,
#925
b101 8
x!
x"
x$
0'
b10 A
b10 D
b10 I
b10 Q
b10 T
b11 9
b10 E
1,
#930
0,
#935
b1 >
b1 C
b1 M
b1 ?
b1 L
b1 O
b1 Y
b10 <
b10 S
b10 W
b11 8
0!
1"
0$
1'
b101 9
1,
#940
0,
#945
1)
0(
b110 8
x!
x"
x$
0'
b1 A
b1 D
b1 I
b1 Q
b1 T
b11 9
b1 E
1,
#950
0,
#955
b1 +
b1 B
b0 8
1*
b110 9
1,
#960
0,
#965
bz +
bz B
b1 8
0*
b0 9
1,
#970
b0 8
b11 0
0/
0,
#975
1,
#980
b1 8
1/
0,
#985
b11000111 >
b11000111 C
b11000111 M
b10 8
0#
1$
1'
b1 9
1,
#990
b110011 >
b110011 C
b110011 M
b110011 -
b110011 :
b110011 K
b110011 N
0,
#995
1(
0)
b110011 =
b110011 F
b110011 P
b110011 A
b110011 D
b110011 I
b110011 Q
b110011 T
b11 8
1#
x$
1&
0'
b110011 E
b10 9
1,
#1000
b1010 =
b1010 F
b1010 P
b1010 -
b1010 :
b1010 K
b1010 N
0,
#1005
b101 8
x#
0&
b1010 @
b1010 G
b1010 J
b1010 R
b1010 U
b11 9
b1010 H
1,
#1010
0,
#1015
b1010 ;
b1010 V
b1010 X
b101001 ?
b101001 L
b101001 O
b101001 Y
b110011 <
b110011 S
b110011 W
b101001 >
b101001 C
b101001 M
b11 8
0!
1"
0$
1'
b101 9
1,
#1020
0,
#1025
b101 8
x!
x"
x$
0'
b101001 A
b101001 D
b101001 I
b101001 Q
b101001 T
b11 9
b101001 E
1,
#1030
0,
#1035
b11111 >
b11111 C
b11111 M
b11111 ?
b11111 L
b11111 O
b11111 Y
b101001 <
b101001 S
b101001 W
b11 8
0!
1"
0$
1'
b101 9
1,
#1040
0,
#1045
b101 8
x!
x"
x$
0'
b11111 A
b11111 D
b11111 I
b11111 Q
b11111 T
b11 9
b11111 E
1,
#1050
0,
#1055
b10101 >
b10101 C
b10101 M
b10101 ?
b10101 L
b10101 O
b10101 Y
b11111 <
b11111 S
b11111 W
b11 8
0!
1"
0$
1'
b101 9
1,
#1060
0,
#1065
b101 8
x!
x"
x$
0'
b10101 A
b10101 D
b10101 I
b10101 Q
b10101 T
b11 9
b10101 E
1,
#1070
0,
#1075
b1011 >
b1011 C
b1011 M
b1011 ?
b1011 L
b1011 O
b1011 Y
b10101 <
b10101 S
b10101 W
b11 8
0!
1"
0$
1'
b101 9
1,
#1080
0,
#1085
b101 8
x!
x"
x$
0'
b1011 A
b1011 D
b1011 I
b1011 Q
b1011 T
b11 9
b1011 E
1,
#1090
0,
#1095
b1 >
b1 C
b1 M
b1 ?
b1 L
b1 O
b1 Y
b1011 <
b1011 S
b1011 W
b11 8
0!
1"
0$
1'
b101 9
1,
#1100
0,
#1105
0(
1%
b100 8
x!
x"
x$
0'
b1 A
b1 D
b1 I
b1 Q
b1 T
b11 9
b1 E
1,
#1110
0,
#1115
b1 ;
b1 V
b1 X
b1001 ?
b1001 L
b1001 O
b1001 Y
b1010 <
b1010 S
b1010 W
b1001 =
b1001 F
b1001 P
b11 8
1!
0"
0#
1&
b100 9
1,
#1120
0,
#1125
b100 8
x!
x"
x#
0&
b1001 @
b1001 G
b1001 J
b1001 R
b1001 U
b11 9
b1001 H
1,
#1130
0,
#1135
b1000 =
b1000 F
b1000 P
b1000 ?
b1000 L
b1000 O
b1000 Y
b1001 <
b1001 S
b1001 W
b11 8
1!
0"
0#
1&
b100 9
1,
#1140
0,
#1145
b100 8
x!
x"
x#
0&
b1000 @
b1000 G
b1000 J
b1000 R
b1000 U
b11 9
b1000 H
1,
#1150
0,
#1155
b111 =
b111 F
b111 P
b111 ?
b111 L
b111 O
b111 Y
b1000 <
b1000 S
b1000 W
b11 8
1!
0"
0#
1&
b100 9
1,
#1160
0,
#1165
b100 8
x!
x"
x#
0&
b111 @
b111 G
b111 J
b111 R
b111 U
b11 9
b111 H
1,
#1170
0,
