light.v
module light (clk, light);
    input clk;
    output reg [2 : 0] light;
    parameter RED = 3'b100, YELLOW = 3'b001, GREEN = 3'b010;
    parameter S0 = 2'b00, S1 = 2'b01, S2 = 2'b10;
    reg [1 : 0] state;

    always @(posedge clk) begin
        case (state)
            S0 : state <= S1;
            S1 : state <= S2;
            S2 : state <= S0;
            default: state <= S0;
        endcase
    end

    always @(state) begin
        case (state) 
            S0 : light = RED;
            S1 : light = GREEN;
            S2 : light = YELLOW;
            default: light = RED;
        endcase
    end
endmodule

light_tb.v
module light_tb;
    reg clk;
    wire [2 : 0] light;

    light DUT (.clk(clk), .light(light));

    initial begin
        clk = 0;
    end
    always #5 clk = ~clk;

    initial begin
        $dumpfile("light.vcd");
        $dumpvars(0, light_tb);
        $monitor($time, " ", "light = %3b", light);
        #200;
        #10 $finish;
    end
endmodule

light.vcd
$date
	Fri Feb 07 10:04:10 2025
$end
$version
	Icarus Verilog
$end
$timescale
	1s
$end
$scope module light_tb $end
$var wire 3 ! light [2:0] $end
$var reg 1 " clk $end
$scope module DUT $end
$var wire 1 " clk $end
$var parameter 3 # GREEN $end
$var parameter 3 $ RED $end
$var parameter 2 % S0 $end
$var parameter 2 & S1 $end
$var parameter 2 ' S2 $end
$var parameter 3 ( YELLOW $end
$var reg 3 ) light [2:0] $end
$var reg 2 * state [1:0] $end
$upscope $end
$upscope $end
$enddefinitions $end
$comment Show the parameter values. $end
$dumpall
b1 (
b10 '
b1 &
b0 %
b100 $
b10 #
$end
#0
$dumpvars
bx *
bx )
0"
bx !
$end
#5
b100 !
b100 )
b0 *
1"
#10
0"
#15
b10 !
b10 )
b1 *
1"
#20
0"
#25
b1 !
b1 )
b10 *
1"
#30
0"
#35
b100 !
b100 )
b0 *
1"
#40
0"
#45
b10 !
b10 )
b1 *
1"
#50
0"
#55
b1 !
b1 )
b10 *
1"
#60
0"
#65
b100 !
b100 )
b0 *
1"
#70
0"
#75
b10 !
b10 )
b1 *
1"
#80
0"
#85
b1 !
b1 )
b10 *
1"
#90
0"
#95
b100 !
b100 )
b0 *
1"
#100
0"
#105
b10 !
b10 )
b1 *
1"
#110
0"
#115
b1 !
b1 )
b10 *
1"
#120
0"
#125
b100 !
b100 )
b0 *
1"
#130
0"
#135
b10 !
b10 )
b1 *
1"
#140
0"
#145
b1 !
b1 )
b10 *
1"
#150
0"
#155
b100 !
b100 )
b0 *
1"
#160
0"
#165
b10 !
b10 )
b1 *
1"
#170
0"
#175
b1 !
b1 )
b10 *
1"
#180
0"
#185
b100 !
b100 )
b0 *
1"
#190
0"
#195
b10 !
b10 )
b1 *
1"
#200
0"
#205
b1 !
b1 )
b10 *
1"
