FSM.v
`ifndef FSM_V
`define FSM_V
module MSSV (
    inp, outp, done, clk, rst, detect, sum
);
    input clk, rst;
    input [2 : 0] inp;
    output reg [2 : 0] outp;
    output reg done;
    output reg [1 : 0] detect;
    output reg [3 : 0] sum;
    reg [2 : 0] temp [3 : 0];
    // wire [2 : 0] temp;
    reg [2 : 0] PState, NState;
    parameter S0 = 3'b000, S1 = 3'b001, S2 = 3'b010, S3 = 3'b011, S4 = 3'b100;

    // assign temp = inp;   
    always @(posedge clk or posedge rst) begin
        if (rst) begin
            PState <= S0;
        end
        else PState <= NState;
    end

    // always @(*) begin
    //     if ((PState == S4) && (temp % 2 == 0)) begin
    //         detect = 2'd1;
    //     end
    //     else if ((PState != S4) && (temp % 2 != 0)) begin
    //         detect = 2'd2;
    //     end
    // end

    always @(*) begin
        case (PState)
            S0 : begin
                outp = 3'd0;
                sum = 4'd0;
                detect = 2'b0;
                done = 0;
                if (inp == 3'd0) begin
                    NState = S1;
                end 
                else begin
                    NState = S0;
                end
            end
            S1 : begin
                outp = 3'd0;
                temp[0] = outp;
                detect = 2'b0;
                done = 0;
                if (inp == 3'd6) begin
                    NState = S2;
                end
                else if (inp == 3'd0) begin
                    NState = S1;    
                end
            end
            S2 : begin
                outp = 3'd6;
                temp[1] = outp;
                detect = 2'b0;
                sum = 4'd0;
                temp[1] = outp;
                done = 0;
                if (inp == 3'd4) begin
                    NState = S3;
                end
                else if (inp == 3'd0) begin
                    NState = S1;
                end
                else NState = S0;
            end
            S3 : begin 
                outp = 3'd4;
                temp[2] = outp;
                detect = 2'd0;
                sum = 4'd0;
                done = 0;
                if (inp == 3'd2) begin
                    NState = S4;
                end
                else if (inp == 3'd0) begin
                    NState = S1;
                end
                else if (inp != 3'd2) begin
                    NState = S0;
                end
            end 
            S4 : begin
                outp = 3'd2;
                temp[3] = outp;
                if ((PState == S4) && (outp % 2 == 0)) begin
                    detect = 2'd1;
                end
                else detect = 2'd2;
                done = 1;
                sum = temp[0] + temp[1] + temp[2] + temp[3];
                NState = S0;
            end
            default: 
                outp = 3'd0;
        endcase
    end
endmodule

`endif

tbFSM.v
`timescale 1ns / 1ps
`include "FSM.v"
module MSSV_tb;
    reg clk, rst;
    reg [2:0] inp;
    wire [2:0] outp;
    wire [1 : 0] detect;
    wire [3 : 0] sum;
    wire done;
    
    MSSV uut (
        .clk(clk), 
        .rst(rst), 
        .inp(inp), 
        .detect(detect),
        .outp(outp), 
        .done(done),
        .sum(sum)
    );

    always #5 clk = ~clk; // Clock period = 10ns
    
    initial begin
        $dumpfile("MSSV_tb.vcd");
        $dumpvars(0, MSSV_tb);
        
        clk = 0;
        rst = 1;
        inp = 3'd0;
        
        #10 rst = 0;
        
        // Test all possible cases
        #10 inp = 3'd0; // Valid case: Transition to S1
        #10 inp = 3'd6; // Valid case: Transition to S2
        #10 inp = 3'd4; // Valid case: Transition to S3
        #10 inp = 3'd2; // Valid case: Back to S0
        
        // Invalid test cases (4 groups)
        #10 inp = 3'd0; #10 inp = 3'd6; // Invalid sequence 1
        #10 inp = 3'd4; #10 inp = 3'd3; // Invalid sequence 2
        #10 inp = 3'd0; #10 inp = 3'd6; // Invalid sequence 3 (looping S1)
        #10 inp = 3'd4; #10 inp = 3'd1; // Invalid sequence 4 (wrong transition)
        
        #10 inp = 3'd0; // Restarting valid sequence
        #10 inp = 3'd6;
        #10 inp = 3'd4;
        #10 inp = 3'd2;
        
        #1000;
        $finish;
    end

    initial begin
        $monitor($time, " ", "outp = %d, done = %b, detect = %d, sum = %d", outp, done, detect, sum);
    end
endmodule

MSSV_tb.vcd
$date
	Wed Apr 09 10:11:47 2025
$end
$version
	Icarus Verilog
$end
$timescale
	1ps
$end
$scope module MSSV_tb $end
$var wire 4 ! sum [3:0] $end
$var wire 3 " outp [2:0] $end
$var wire 1 # done $end
$var wire 2 $ detect [1:0] $end
$var reg 1 % clk $end
$var reg 3 & inp [2:0] $end
$var reg 1 ' rst $end
$scope module uut $end
$var wire 1 % clk $end
$var wire 3 ( inp [2:0] $end
$var wire 1 ' rst $end
$var parameter 3 ) S0 $end
$var parameter 3 * S1 $end
$var parameter 3 + S2 $end
$var parameter 3 , S3 $end
$var parameter 3 - S4 $end
$var reg 3 . NState [2:0] $end
$var reg 3 / PState [2:0] $end
$var reg 2 0 detect [1:0] $end
$var reg 1 # done $end
$var reg 3 1 outp [2:0] $end
$var reg 4 2 sum [3:0] $end
$upscope $end
$upscope $end
$enddefinitions $end
$comment Show the parameter values. $end
$dumpall
b100 -
b11 ,
b10 +
b1 *
b0 )
$end
#0
$dumpvars
b0 2
b0 1
b0 0
b0 /
b1 .
b0 (
1'
b0 &
0%
b0 $
0#
b0 "
b0 !
$end
#5000
1%
#10000
0%
0'
#15000
b1 /
1%
#20000
0%
#25000
1%
#30000
b10 .
0%
b110 &
b110 (
#35000
b0 .
b110 "
b110 1
b10 /
1%
#40000
b11 .
0%
b100 &
b100 (
#45000
b0 .
b100 "
b100 1
b11 /
1%
#50000
b100 .
0%
b10 &
b10 (
#55000
b0 .
b1100 !
b1100 2
1#
b1 $
b1 0
b10 "
b10 1
b100 /
1%
#60000
0%
b0 &
b0 (
#65000
b1 .
0#
b0 $
b0 0
b0 !
b0 2
b0 "
b0 1
b0 /
1%
#70000
b0 .
0%
b110 &
b110 (
#75000
1%
#80000
0%
b100 &
b100 (
#85000
1%
#90000
0%
b11 &
b11 (
#95000
1%
#100000
b1 .
0%
b0 &
b0 (
#105000
b1 /
1%
#110000
b10 .
0%
b110 &
b110 (
#115000
b0 .
b110 "
b110 1
b10 /
1%
#120000
b11 .
0%
b100 &
b100 (
#125000
b0 .
b100 "
b100 1
b11 /
1%
#130000
0%
b1 &
b1 (
#135000
b0 "
b0 1
b0 /
1%
#140000
b1 .
0%
b0 &
b0 (
#145000
b1 /
1%
#150000
b10 .
0%
b110 &
b110 (
#155000
b0 .
b110 "
b110 1
b10 /
1%
#160000
b11 .
0%
b100 &
b100 (
#165000
b0 .
b100 "
b100 1
b11 /
1%
#170000
b100 .
0%
b10 &
b10 (
#175000
b0 .
b1100 !
b1100 2
1#
b1 $
b1 0
b10 "
b10 1
b100 /
1%
#180000
0%
#185000
0#
b0 $
b0 0
b0 !
b0 2
b0 "
b0 1
b0 /
1%
