mux16to1_pure.v
module mux16to1 (
    input  [15:0]  in,
    input [3:0] sel,
    output out
);
    assign out = in[sel];
endmodule

mux16to1_pure_tb.v
module mux16to1_tb;
    reg [15:0] in;
    reg [3:0] sel;
    wire out;
    mux16to1 DUT (.in(in), .sel(sel), .out(out));
    initial begin
        $dumpfile("mux16to1.vcd");
        $dumpvars(0, mux16to1_tb);
        $monitor($time, " ", "in = %h, sel = %h, out = %b", in, sel, out);

        in = 16'b1111000010100101;

        //Test 1
        sel = 4'h0;
        #5;
        //Test 2
        sel = 4'h1;
        #5;
        //Test 3
        sel = 4'h2;
        #5;
        //Test 4
        sel = 4'h3;
        #5;
        //Test 5
        sel = 4'h4;
        #5;
        //Test 6
        sel = 4'h5;
        #5;
        //Test 7
        sel = 4'h6;
        #5;
        //Test 8
        sel = 4'h7;
        #5;
        //Test 9
        sel = 4'h8;
        #5;
        //Test 10
        sel = 4'h9;
        #5;
        //Test 11
        sel = 4'hA;
        #5;
        //Test 12
        sel = 4'hB;
        #5;
        //Test 13
        sel = 4'hC;
        #5;
        //Test 14
        sel = 4'hD;
        #5;
        //Test 15
        sel = 4'hE;
        #5;
        //Test 16
        sel = 4'hF;
        #5;
    end
endmodule

mux16to1.vcd
$date
	Tue Jan 21 10:39:50 2025
$end
$version
	Icarus Verilog
$end
$timescale
	1s
$end
$scope module mux16to1_tb $end
$var wire 1 ! out $end
$var reg 16 " in [15:0] $end
$var reg 4 # sel [3:0] $end
$scope module DUT $end
$var wire 16 $ in [15:0] $end
$var wire 4 % sel [3:0] $end
$var wire 1 ! out $end
$upscope $end
$upscope $end
$enddefinitions $end
$comment Show the parameter values. $end
$dumpall
$end
#0
$dumpvars
b0 %
b1111000010100101 $
b0 #
b1111000010100101 "
1!
$end
#5
0!
b1 #
b1 %
#10
1!
b10 #
b10 %
#15
0!
b11 #
b11 %
#20
b100 #
b100 %
#25
1!
b101 #
b101 %
#30
0!
b110 #
b110 %
#35
1!
b111 #
b111 %
#40
0!
b1000 #
b1000 %
#45
b1001 #
b1001 %
#50
b1010 #
b1010 %
#55
b1011 #
b1011 %
#60
1!
b1100 #
b1100 %
#65
b1101 #
b1101 %
#70
b1110 #
b1110 %
#75
b1111 #
b1111 %
