odd_even.v
module oddeven (
    clk, result, x
);
    input clk, x;
    output reg result;
    reg even_odd;
    parameter EVEN = 0, ODD = 1;
    // always @(posedge clk) begin
    //     case (even_odd)
    //         EVEN : 
    //             begin 
    //                 result <= x ? 1 : 0; 
    //                 even_odd <= x ? ODD : EVEN;
    //             end
    //         ODD : 
    //             begin 
    //                 result <= x ? 0 : 1; 
    //                 even_odd <= x ? EVEN : ODD;
    //             end
    //         default: even_odd <= EVEN;
    //     endcase
    // end
    always @(posedge clk) 
        begin
            case (even_odd)
            EVEN : even_odd <= x ? ODD : EVEN;
            ODD : even_odd <= x ? EVEN : ODD;
            default: even_odd <= EVEN;
            endcase
        end
    always @(even_odd)
        begin
            case (even_odd)
                EVEN : result = 0;
                ODD : result = 1;
                default : result = 0; 
            endcase
        end
endmodule

odd_even_tb.v
module even_odd_tb;
    reg clk, x;
    wire result;

    oddeven DUT (.clk(clk), .x(x), .result(result));

    initial begin
        clk = 0;
    end
    always #5 clk = ~clk;
    initial begin
        $dumpfile("odd_even.vcd");
        $dumpvars(0, even_odd_tb);
        $monitor($time, " ", "x = %b, result = %b", x, result);

        #2 x = 0;
        #10 x = 1;
        #10 x = 0;
        #10 x = 0;
        #10 x = 1;
        #10 x = 1;
        #10 x = 0;
        #10 x = 1;
        #10 $finish;
    end
endmodule

odd_even.vcd
$date
	Thu Feb 06 17:17:10 2025
$end
$version
	Icarus Verilog
$end
$timescale
	1s
$end
$scope module even_odd_tb $end
$var wire 1 ! result $end
$var reg 1 " clk $end
$var reg 1 # x $end
$scope module DUT $end
$var wire 1 " clk $end
$var wire 1 # x $end
$var parameter 32 $ EVEN $end
$var parameter 32 % ODD $end
$var reg 1 & even_odd $end
$var reg 1 ! result $end
$upscope $end
$upscope $end
$enddefinitions $end
$comment Show the parameter values. $end
$dumpall
b1 %
b0 $
$end
#0
$dumpvars
x&
x#
0"
x!
$end
#2
0#
#5
0!
0&
1"
#10
0"
#12
1#
#15
1!
1&
1"
#20
0"
#22
0#
#25
1"
#30
0"
#35
1"
#40
0"
#42
1#
#45
0!
0&
1"
#50
0"
#55
1!
1&
1"
#60
0"
#62
0#
#65
1"
#70
0"
#72
1#
#75
0!
0&
1"
