UpDownCounter.v
module updown (mode, clr, load, din, clk, count);
    input mode, clr, load, clk;
    input [0 : 7] din;
    output reg [0 : 7] count;

    always @(posedge clk) begin
        if (load) begin
            count <= din;
        end
        else if (clr) begin
            count <= 0;
        end
        else if (mode) begin
            count <= count + 1;
        end
        else begin
            count <= count - 1;
        end
    end
endmodule

UpDownCounter_tb.v
module updown_tb;
    reg mode, clr, clk, load;
    reg [7:0] din;
    wire [7:0] count;

    updown DUT (.mode(mode), .clr(clr), .clk(clk), .load(load), .din(din), .count(count));

    initial begin
        clk = 0;
        forever begin
            #5 clk = ~clk;
        end
    end

    initial begin
        $dumpfile("updowm.vcd");
        $dumpvars(0, updown_tb);

        $monitor($time, " ", "mode = %b, clr = %b, load = %b, din = %d, count = %d", mode, clr, load, din, count);
        clr = 1 ;
        mode = 0 ;
        load = 0 ;
        din = 0 ;
        #10;
        clr = 0;
        mode = 1;
        #10;
        #100;
        mode = 0;
        #10;
        #50;
        load = 1;
        din = 5;
        #10;
        $finish;

       
    end
endmodule

updowm.vcd
$date
	Thu Jan 30 13:11:31 2025
$end
$version
	Icarus Verilog
$end
$timescale
	1s
$end
$scope module updown_tb $end
$var wire 8 ! count [7:0] $end
$var reg 1 " clk $end
$var reg 1 # clr $end
$var reg 8 $ din [7:0] $end
$var reg 1 % load $end
$var reg 1 & mode $end
$scope module DUT $end
$var wire 1 " clk $end
$var wire 1 # clr $end
$var wire 8 ' din [0:7] $end
$var wire 1 % load $end
$var wire 1 & mode $end
$var reg 8 ( count [0:7] $end
$upscope $end
$upscope $end
$enddefinitions $end
$comment Show the parameter values. $end
$dumpall
$end
#0
$dumpvars
bx (
b0 '
0&
0%
b0 $
1#
0"
bx !
$end
#5
b0 !
b0 (
1"
#10
0"
1&
0#
#15
b1 !
b1 (
1"
#20
0"
#25
b10 !
b10 (
1"
#30
0"
#35
b11 !
b11 (
1"
#40
0"
#45
b100 !
b100 (
1"
#50
0"
#55
b101 !
b101 (
1"
#60
0"
#65
b110 !
b110 (
1"
#70
0"
#75
b111 !
b111 (
1"
#80
0"
#85
b1000 !
b1000 (
1"
#90
0"
#95
b1001 !
b1001 (
1"
#100
0"
#105
b1010 !
b1010 (
1"
#110
0"
#115
b1011 !
b1011 (
1"
#120
0"
0&
#125
b1010 !
b1010 (
1"
#130
0"
#135
b1001 !
b1001 (
1"
#140
0"
#145
b1000 !
b1000 (
1"
#150
0"
#155
b111 !
b111 (
1"
#160
0"
#165
b110 !
b110 (
1"
#170
0"
#175
b101 !
b101 (
1"
#180
0"
b101 $
b101 '
1%
